setup.py
jdm_distributions/Binomialdistribution.py
jdm_distributions/Gaussiandistribution.py
jdm_distributions/Generaldistribution.py
jdm_distributions/__init__.py
jdm_distributions.egg-info/PKG-INFO
jdm_distributions.egg-info/SOURCES.txt
jdm_distributions.egg-info/dependency_links.txt
jdm_distributions.egg-info/not-zip-safe
jdm_distributions.egg-info/top_level.txt